airflow/providers/__init__.py
airflow/providers/y42demo/__init__.py
airflow/providers/y42demo/get_provider_info.py
airflow/providers/y42demo/hooks/__init__.py
airflow/providers/y42demo/hooks/orchestration.py
airflow/providers/y42demo/provider.yaml
airflow/providers/y42demo/sensors/__init__.py
airflow/providers/y42demo/sensors/orchestration.py
apache_airflow_providers_y42demo2-0.1.10.dist-info/WHEEL
apache_airflow_providers_y42demo2-0.1.10.dist-info/METADATA
apache_airflow_providers_y42demo2-0.1.10.dist-info/RECORD
