Metadata-Version: 2.1
Name: apache-airflow-providers-y42demo2
Version: 0.1.10
Summary: This is a provider package for Y42 provider
Home-page: https://www.y42.com
License: Apache-2.0
Keywords: airflow,y42
Author: Y42
Author-email: dev@y42.com
Maintainer: Y42
Maintainer-email: dev@y42.com
Requires-Python: >=3.7,<4.0
Classifier: Framework :: Apache Airflow
Classifier: Framework :: Apache Airflow :: Provider
Classifier: License :: OSI Approved :: Apache Software License
Classifier: Programming Language :: Python :: 3
Classifier: Programming Language :: Python :: 3.10
Classifier: Programming Language :: Python :: 3.7
Classifier: Programming Language :: Python :: 3.8
Classifier: Programming Language :: Python :: 3.9
Requires-Dist: apache-airflow (>=2.2.0,<3.0.0)
Project-URL: Repository, https://github.com/goes-funky/orchestration-api-v2
